ot2ools/__init__.py
ot2ools/_utils.py
ot2ools/_version.py
ot2ools/constant_stock.py
ot2ools/pool_by_volume.py
ot2ools/variable_stock.py
weigel_ot2ools-0.1.6.dist-info/METADATA
weigel_ot2ools-0.1.6.dist-info/WHEEL
weigel_ot2ools-0.1.6.dist-info/entry_points.txt
weigel_ot2ools-0.1.6.dist-info/top_level.txt
weigel_ot2ools-0.1.6.dist-info/RECORD
