Metadata-Version: 2.1
Name: weigel-ot2ools
Version: 0.1.6
Summary: Add your description here
Requires-Python: >=3.8
Requires-Dist: tqdm
